crimsonslate_portfolio/.gitignore
crimsonslate_portfolio/__init__.py
crimsonslate_portfolio/admin.py
crimsonslate_portfolio/apps.py
crimsonslate_portfolio/forms.py
crimsonslate_portfolio/models.py
crimsonslate_portfolio/tests.py
crimsonslate_portfolio/urls.py
crimsonslate_portfolio/validators.py
crimsonslate_portfolio/management/__init__.py
crimsonslate_portfolio/management/commands/__init__.py
crimsonslate_portfolio/management/commands/_private.py
crimsonslate_portfolio/management/commands/tailwind.py
crimsonslate_portfolio/static/crimsonslate_portfolio/css/input.css
crimsonslate_portfolio/static/crimsonslate_portfolio/css/output.css
crimsonslate_portfolio/static/crimsonslate_portfolio/js/htmx.min.js
crimsonslate_portfolio/templates/portfolio/contact.html
crimsonslate_portfolio/templates/portfolio/layout.html
crimsonslate_portfolio/templates/portfolio/login.html
crimsonslate_portfolio/templates/portfolio/logout.html
crimsonslate_portfolio/templates/portfolio/icons/discord.svg
crimsonslate_portfolio/templates/portfolio/icons/facebook.svg
crimsonslate_portfolio/templates/portfolio/icons/instagram.svg
crimsonslate_portfolio/templates/portfolio/icons/reddit.svg
crimsonslate_portfolio/templates/portfolio/icons/tiktok.svg
crimsonslate_portfolio/templates/portfolio/icons/twitter.svg
crimsonslate_portfolio/templates/portfolio/icons/youtube.svg
crimsonslate_portfolio/templates/portfolio/partials/_contact.html
crimsonslate_portfolio/templates/portfolio/partials/_login.html
crimsonslate_portfolio/templates/portfolio/partials/_logout.html
crimsonslate_portfolio/templates/portfolio/tags/create.html
crimsonslate_portfolio/templates/portfolio/tags/delete.html
crimsonslate_portfolio/templates/portfolio/tags/update.html
crimsonslate_portfolio/templates/portfolio/tags/widget.html
crimsonslate_portfolio/templates/portfolio/tags/partials/_create.html
crimsonslate_portfolio/templates/portfolio/tags/partials/_delete.html
crimsonslate_portfolio-9.2.0.dist-info/METADATA
crimsonslate_portfolio-9.2.0.dist-info/WHEEL
crimsonslate_portfolio-9.2.0.dist-info/licenses/COPYING
crimsonslate_portfolio-9.2.0.dist-info/RECORD
