Metadata-Version: 2.4
Name: crimsonslate_portfolio
Version: 9.2.0
Summary: Django Portfolio application by crimsonslate
Project-URL: Homepage, https://github.com/crimsonslate/portfolio
Project-URL: Repository, https://github.com/crimsonslate/portfolio
Project-URL: Documentation, https://crimsonslate-portfolio.readthedocs.io/en/latest
Author-email: Blake Nall <dev@darthnall.com>, Constantine Kapatos <kapatos.constantine@gmail.com>
License-File: COPYING
Classifier: License :: OSI Approved :: GNU General Public License v3 or later (GPLv3+)
Classifier: Operating System :: OS Independent
Classifier: Programming Language :: Python :: 3
Classifier: Programming Language :: Python :: 3.12
Requires-Python: >=3.12
Requires-Dist: django-filer[heif]>=3.3.1
Requires-Dist: django-storages[s3]>=1.14.4
Requires-Dist: django>=5.1.6
Requires-Dist: emoji>=2.14.1
Requires-Dist: pillow>=11.1.0
Requires-Dist: setuptools>=76.0.0
